{
  "openapi": "3.0.3",
  "info": {
    "title": "Music Streaming Service - OpenAPI 3.0",
    "description": "The console below provides you with all endpoints and parameters available for this REST API.",
    "termsOfService": "http://swagger.io/terms/",
    "contact": {
      "email": "losBandoleros@gmail.com"
    },
    "license": {
      "name": "Apache 2.0",
      "url": "http://www.apache.org/licenses/LICENSE-2.0.html"
    },
    "version": "1.0.0"
  },
  "externalDocs": {
    "description": "Find out more about Swagger",
    "url": "http://swagger.io"
  },
  "servers": [
    {
      "url": "https://virtserver.swaggerhub.com/NUNOROLEITE_1/LOS_BANDOLEROS_PSIDI/1.0.0"
    }
  ],
  "tags": [
    {
        "name": "Authz",
        "description": ""
      },
    {
      "name": "Plans",
      "description": "Everything about our plans service"
    },
    {
      "name": "Subscriptions",
      "description": "All about subscription service"
    },
    {
      "name": "Dashboard",
      "description": "Provides all important data about available services"
    }
  ],
  "paths": {
    "/authz/login": {
        "post": {
          "tags": ["Authz"],
          "summary": "authenticates user",
          "description": "returns the authentication ID token (JWT) to use in further API calls.",
          "responses": {
            "200": {
              "description": "OK",
              "content": {
                "application/json": {
                  "schema": {
                    "$ref": "#/components/schemas/AllPlans"
                  }
                }
              }
            },
            "404": {
              "description": "Not Found"
            },
            "500": {
              "description": "Internal Server Error"
            }
          }
        }
      },
    "/plans": {
      "get": {
        "tags": ["Plans"],
        "summary": "Shows all available plans",
        "description": "Shows all available plans and their details",
        "responses": {
          "200": {
            "description": "OK",
            "content": {
              "application/json": {
                "schema": {
                  "$ref": "#/components/schemas/AllPlans"
                }
              }
            }
          },
          "404": {
            "description": "Not Found"
          },
          "500": {
            "description": "Internal Server Error"
          }
        }
      }
    },
    "/plan/{id}": {
      "get": {
        "tags": ["Plans"],
        "summary": "Shows available plans by id",
        "description": "From all available plans it is possible to select one by its own identifier",
        "parameters": [
          {
            "name": "id",
            "in": "path",
            "description": "Numeric ID of the plan to get",
            "required": true,
            "style": "simple",
            "explode": false,
            "schema": {
              "type": "integer"
            }
          }
        ],
        "responses": {
          "200": {
            "description": "OK",
            "content": {
              "application/json": {
                "schema": {
                  "$ref": "#/components/schemas/Plans"
                }
              }
            }
          },
          "404": {
            "description": "Not Found"
          },
          "500": {
            "description": "Internal Server Error"
          }
        }
      }
    },
    "/plan/newplan": {
      "post": {
        "tags": ["Plans"],
        "summary": "Create a new plan",
        "description": "Create a new plan and define different characteristics for it",
        "responses": {
          "201": {
            "description": "Created",
            "content": {
              "application/json": {
                "schema": {
                  "$ref": "#/components/schemas/Plans"
                }
              }
            }
          },
          "400": {
            "description": "Bad Request"
          },
          "401": {
            "description": "Unauthorized"
          },
          "404": {
            "description": "Not Found"
          },
          "500": {
            "description": "Internal Server Error"
          }
        }
      }
    },
    "/plan/{id}/editplan": {
      "put": {
        "tags": ["Plans"],
        "summary": "Edit an existing plan",
        "description": "Edit the characteristics of an existing plan through its own identifier",
        "parameters": [
          {
            "name": "id",
            "in": "path",
            "description": "Numeric ID of the plan we want to edit",
            "required": true,
            "style": "simple",
            "explode": false,
            "schema": {
              "type": "integer"
            }
          }
        ],
        "requestBody": {
          "description": "Edit an existing plan",
          "content": {
            "application/json": {
              "schema": {
                "$ref": "#/components/schemas/Plans"
              }
            }
          },
          "required": true
        },
        "responses": {
          "200": {
            "description": "OK",
            "content": {
              "application/json": {
                "schema": {
                  "$ref": "#/components/schemas/Plans"
                }
              }
            }
          },
          "201": {
            "description": "Created",
            "content": {
              "application/json": {
                "schema": {
                  "$ref": "#/components/schemas/Plans"
                }
              }
            }
          },
          "400": {
            "description": "Bad Request"
          },
          "401": {
            "description": "Unauthorized"
          },
          "403": {
            "description": "Forbidden"
          },
          "404": {
            "description": "Not Found"
          },
          "500": {
            "description": "Internal Server Error"
          }
        }
      }
    },
    "/plan/{id}/deactivate": {
      "put": {
        "tags": ["Plans"],
        "summary": "Deactivate an existing plan",
        "description": "Deactivate an existing plan through its own identifier",
        "parameters": [
          {
            "name": "id",
            "in": "path",
            "description": "Numeric ID of the plan we want to deactivate",
            "required": true,
            "style": "simple",
            "explode": false,
            "schema": {
              "type": "integer"
            }
          }
        ],
        "requestBody": {
          "description": "Deactivate an existing plan",
          "content": {
            "application/json": {
              "schema": {
                "$ref": "#/components/schemas/Plans"
              }
            }
          },
          "required": true
        },
        "responses": {
          "200": {
            "description": "OK",
            "content": {
              "application/json": {
                "schema": {
                  "$ref": "#/components/schemas/Plans"
                }
              }
            }
          },
          "201": {
            "description": "Created",
            "content": {
              "application/json": {
                "schema": {
                  "$ref": "#/components/schemas/Plans"
                }
              }
            }
          },
          "400": {
            "description": "Bad Request"
          },
          "401": {
            "description": "Unauthorized"
          },
          "403": {
            "description": "Forbidden"
          },
          "404": {
            "description": "Not Found"
          },
          "500": {
            "description": "Internal Server Error"
          }
        }
      }
    },
    "/plans/{id}/subscribe": {
      "post": {
        "tags": ["Subscriptions"],
        "summary": "Subscribe an existing plan !!!! CORRIGIR !!!!",
        "description": "Subscribe an existing plan through its own identifier",
        "parameters": [
          {
            "name": "id",
            "in": "path",
            "description": "Numeric ID of the plan we want to subscribe",
            "required": true,
            "style": "simple",
            "explode": false,
            "schema": {
              "type": "integer"
            }
          },
          {
            "name": "subscribe",
            "in": "query",
            "description": "Shows us if the user subscribed or not the plan",
            "required": true,
            "style": "form",
            "explode": true,
            "schema": {
              "type": "boolean"
            }
          }
        ],
        "requestBody": {
          "description": "Subscribe an existing plan",
          "content": {
            "application/json": {
              "schema": {
                "$ref": "#/components/schemas/Subscription"
              }
            }
          },
          "required": true
        },
        "responses": {
          "201": {
            "description": "Created",
            "content": {
              "application/json": {
                "schema": {
                  "$ref": "#/components/schemas/Subscription"
                }
              }
            }
          },
          "400": {
            "description": "Bad Request"
          },
          "401": {
            "description": "Unauthorized"
          },
          "404": {
            "description": "Not Found"
          },
          "500": {
            "description": "Internal Server Error"
          }
        }
      }
    },
    "/subscription/{id}/devices": {
      "get": {
        "tags": ["Subscriptions"],
        "summary": "5.4 - List of subscriber devices ",
        "description": "5.4 - As subscriber I want to list my devices",
        "parameters": [
          {
            "name": "id",
            "in": "path",
            "description": "Numeric ID of the plan we want to subscribe",
            "required": true,
            "style": "simple",
            "explode": false,
            "schema": {
              "type": "integer"
            }
          },
          {
            "name": "subscribe",
            "in": "query",
            "description": "Shows us if the user subscribed or not the plan",
            "required": true,
            "style": "form",
            "explode": true,
            "schema": {
              "type": "boolean"
            }
          }
        ],
        "requestBody": {
          "description": "Subscribe an existing plan",
          "content": {
            "application/json": {
              "schema": {
                "$ref": "#/components/schemas/Subscription"
              }
            }
          },
          "required": true
        },
        "responses": {
          "201": {
            "description": "Created",
            "content": {
              "application/json": {
                "schema": {
                  "$ref": "#/components/schemas/Subscription"
                }
              }
            }
          },
          "400": {
            "description": "Bad Request"
          },
          "401": {
            "description": "Unauthorized"
          },
          "404": {
            "description": "Not Found"
          },
          "500": {
            "description": "Internal Server Error"
          }
        }
      },
     
      "put": {
        "tags": ["Subscriptions"],
        "summary": "5.1 - Subscriber adds a new device to subscription ",
        "description": "5.1 - As subscriber I want to add a new device to my subscription",
        "parameters": [
          {
            "name": "id",
            "in": "path",
            "description": "Numeric ID of the plan we want to subscribe",
            "required": true,
            "style": "simple",
            "explode": false,
            "schema": {
              "type": "integer"
            }
          },
          {
            "name": "subscribe",
            "in": "query",
            "description": "Shows us if the user subscribed or not the plan",
            "required": true,
            "style": "form",
            "explode": true,
            "schema": {
              "type": "boolean"
            }
          }
        ],
        "requestBody": {
          "description": "Subscribe an existing plan",
          "content": {
            "application/json": {
              "schema": {
                "$ref": "#/components/schemas/Subscription"
              }
            }
          },
          "required": true
        },
        "responses": {
          "201": {
            "description": "Created",
            "content": {
              "application/json": {
                "schema": {
                  "$ref": "#/components/schemas/Subscription"
                }
              }
            }
          },
          "400": {
            "description": "Bad Request"
          },
          "401": {
            "description": "Unauthorized"
          },
          "404": {
            "description": "Not Found"
          },
          "500": {
            "description": "Internal Server Error"
          }
        }
      }
    },
    "/subscription/{id}/devices/{id}": {
      "delete": {
        "tags": ["Subscriptions"],
        "summary": "5.2 - Subscriber removes devices from subscription ",
        "description": "5.2. As subscriber I want to remove a device from my subscription",
        "parameters": [
          {
            "name": "id",
            "in": "path",
            "description": "Numeric ID of the plan we want to subscribe",
            "required": true,
            "style": "simple",
            "explode": false,
            "schema": {
              "type": "integer"
            }
          },
          {
            "name": "subscribe",
            "in": "query",
            "description": "Shows us if the user subscribed or not the plan",
            "required": true,
            "style": "form",
            "explode": true,
            "schema": {
              "type": "boolean"
            }
          }
        ],
        "requestBody": {
          "description": "Subscribe an existing plan",
          "content": {
            "application/json": {
              "schema": {
                "$ref": "#/components/schemas/Subscription"
              }
            }
          },
          "required": true
        },
        "responses": {
          "200": {
            "description": "Ok",
            "content": {
              "application/json": {
                "schema": {
                  "$ref": "#/components/schemas/Subscription"
                }
              }
            }
          },
          "400": {
            "description": "Bad Request"
          },
          "401": {
            "description": "Unauthorized"
          },
          "404": {
            "description": "Not Found"
          },
          "500": {
            "description": "Internal Server Error"
          }
        }
      },
      "put": {
        "tags": ["Subscriptions"],
        "summary": "5.3 - Subscriber updates the details of device  ",
        "description": "5.3. As subscriber I want to update the details of my device (name and description)",
        "parameters": [
          {
            "name": "id",
            "in": "path",
            "description": "Numeric ID of the plan we want to subscribe",
            "required": true,
            "style": "simple",
            "explode": false,
            "schema": {
              "type": "integer"
            }
          },
          {
            "name": "subscribe",
            "in": "query",
            "description": "Shows us if the user subscribed or not the plan",
            "required": true,
            "style": "form",
            "explode": true,
            "schema": {
              "type": "boolean"
            }
          }
        ],
        "requestBody": {
          "description": "Subscribe an existing plan",
          "content": {
            "application/json": {
              "schema": {
                "$ref": "#/components/schemas/Subscription"
              }
            }
          },
          "required": true
        },
        "responses": {
          "201": {
            "description": "Created",
            "content": {
              "application/json": {
                "schema": {
                  "$ref": "#/components/schemas/Subscription"
                }
              }
            }
          },
          "400": {
            "description": "Bad Request"
          },
          "401": {
            "description": "Unauthorized"
          },
          "404": {
            "description": "Not Found"
          },
          "500": {
            "description": "Internal Server Error"
          }
        }
      }
    },
   
    "/newsub": {
      "get": {
        "tags": ["Dashboard"],
        "summary": "Displays all new subscritors",
        "description": "Shows all new subscritors in a specific month",
        "responses": {
          "200": {
            "description": "OK",
            "content": {
              "application/json": {
                "schema": {
                  "$ref": "#/components/schemas/NewSubs"
                }
              }
            }
          },
          "404": {
            "description": "Not Found"
          },
          "500": {
            "description": "Internal Server Error"
          }
        }
      }
    },
    "/newcancel": {
      "get": {
        "tags": ["Dashboard"],
        "summary": "Displays all cancellations",
        "description": "Shows all cancellations in a specific month",
        "responses": {
          "200": {
            "description": "OK",
            "content": {
              "application/json": {
                "schema": {
                  "$ref": "#/components/schemas/Cancel"
                }
              }
            }
          },
          "404": {
            "description": "Not Found"
          },
          "500": {
            "description": "Internal Server Error"
          }
        }
      }
    }
  },
  "components": {
    "schemas": {
      "AllPlans": {
        "type": "array",
        "items": {
          "$ref": "#/components/schemas/Plans"
        }
      },
      "Plans": {
        "required": ["id"],
        "type": "object",
        "properties": {
          "id": {
            "type": "integer",
            "format": "int64",
            "example": 0
          },
          "plan": {
            "type": "string"
          },
          "description": {
            "type": "string"
          },
          "number_of_minutes": {
            "type": "string"
          },
          "maximum_number_of_users": {
            "type": "integer",
            "format": "int64",
            "example": 0
          },
          "music_collections": {
            "type": "integer",
            "nullable": true
          },
          "music_suggestions": {
            "type": "string"
          },
          "monthly_fee": {
            "type": "number",
            "format": "currency"
          },
          "anual_fee": {
            "type": "number",
            "format": "currency"
          },
          "status": {
            "type": "boolean"
          }
        }
      },
      "Subscription": {
        "type": "object",
        "properties": {
          "id": {
            "type": "integer",
            "format": "int64",
            "example": 0
          },
          "subscribe": {
            "type": "boolean"
          }
        }
      },
      "NewSubs": {
        "type": "object",
        "properties": {
          "year": {
            "type": "integer",
            "format": "int64",
            "example": 0
          },
          "month": {
            "type": "integer",
            "format": "int64",
            "example": 0
          },
          "new_subscritors": {
            "type": "integer",
            "format": "int64",
            "example": 0
          }
        }
      },
      "Cancel": {
        "type": "object",
        "properties": {
          "year": {
            "type": "integer",
            "format": "int64",
            "example": 0
          },
          "month": {
            "type": "integer",
            "format": "int64",
            "example": 0
          },
          "cancellations": {
            "type": "integer",
            "format": "int64",
            "example": 0
          }
        }
      }
    }
  }
}
